sportsdatabase/__init__.py
sportsdatabase/client.py
sportsdatabase/config.py
sportsdatabase/errors.py
sportsdatabase/http.py
sportsdatabase/types.py
sportsdatabase/endpoints/events.py
sportsdatabase/endpoints/leagues.py
sportsdatabase/endpoints/schedules.py
sportsdatabase/endpoints/scores.py
sportsdatabase/endpoints/teams.py
sportsdatabase-0.0.2.dist-info/METADATA
sportsdatabase-0.0.2.dist-info/WHEEL
sportsdatabase-0.0.2.dist-info/RECORD
