Metadata-Version: 2.4
Name: sportsdatabase
Version: 0.0.2
Summary: Official Python SDK for SportsDatabase.io
Author: SportsDatabase.io
License-Expression: MIT
Requires-Python: >=3.9
Requires-Dist: httpx>=0.24.0
Provides-Extra: dev
Requires-Dist: mypy; extra == 'dev'
Requires-Dist: pytest; extra == 'dev'
Requires-Dist: pytest-asyncio; extra == 'dev'
Requires-Dist: ruff; extra == 'dev'
